<?xml version="1.0" encoding="utf-8"?>
<clothing-items>
 <clothing>
  <id>
   835640196
  </id>
  <name>
   Adidas Jeans N-8682
  </name>
  <category>
   Jeans
  </category>
  <size>
   M
  </size>
  <color>
   Синий
  </color>
  <material>
   Шелк
  </material>
  <price>
   981908
  </price>
  <rating>
   3.35
  </rating>
  <reviews>
   50873
  </reviews>
  <new>
   -
  </new>
  <exclusive>
   yes
  </exclusive>
  <sporty>
   yes
  </sporty>
 </clothing>
 <clothing>
  <id>
   128672015
  </id>
  <name>
   Reebok Belts F-1186
  </name>
  <category>
   Belts
  </category>
  <size>
   S
  </size>
  <color>
   Оранжевый
  </color>
  <material>
   Хлопок
  </material>
  <price>
   664527
  </price>
  <rating>
   1.88
  </rating>
  <reviews>
   513795
  </reviews>
  <exclusive>
   no
  </exclusive>
 </clothing>
 <clothing>
  <id>
   396598543
  </id>
  <name>
   Reebok Sweater C-1141
  </name>
  <category>
   Sweater
  </category>
  <size>
   M
  </size>
  <color>
   Оранжевый
  </color>
  <material>
   Вискоза
  </material>
  <price>
   667724
  </price>
  <rating>
   3.39
  </rating>
  <reviews>
   511550
  </reviews>
  <new>
   +
  </new>
  <sporty>
   no
  </sporty>
 </clothing>
 <clothing>
  <id>
   459743664
  </id>
  <name>
   Lacoste Shoes O-9349
  </name>
  <category>
   Shoes
  </category>
  <size>
   XXL
  </size>
  <color>
   Голубой
  </color>
  <material>
   Полиэстер
  </material>
  <price>
   629508
  </price>
  <rating>
   1.06
  </rating>
  <reviews>
   916783
  </reviews>
  <new>
   +
  </new>
  <exclusive>
   yes
  </exclusive>
  <sporty>
   no
  </sporty>
 </clothing>
 <clothing>
  <id>
   279751058
  </id>
  <name>
   Converse Umbrellas H-7054
  </name>
  <category>
   Umbrellas
  </category>
  <size>
   L
  </size>
  <color>
   Зеленый
  </color>
  <material>
   Шерсть
  </material>
  <price>
   170090
  </price>
  <rating>
   2.94
  </rating>
  <reviews>
   614327
  </reviews>
  <exclusive>
   no
  </exclusive>
  <sporty>
   no
  </sporty>
 </clothing>
 <clothing>
  <id>
   413941395
  </id>
  <name>
   DC Shoes I-2312
  </name>
  <category>
   Shoes
  </category>
  <size>
   XL
  </size>
  <color>
   Фиолетовый
  </color>
  <material>
   Шелк
  </material>
  <price>
   486770
  </price>
  <rating>
   2.17
  </rating>
  <reviews>
   266362
  </reviews>
  <new>
   -
  </new>
  <sporty>
   yes
  </sporty>
 </clothing>
 <clothing>
  <id>
   632292495
  </id>
  <name>
   Brooks Jeans N-6984
  </name>
  <category>
   Jeans
  </category>
  <size>
   S
  </size>
  <color>
   Голубой
  </color>
  <material>
   Вискоза
  </material>
  <price>
   562847
  </price>
  <rating>
   3.96
  </rating>
  <reviews>
   177757
  </reviews>
  <new>
   -
  </new>
  <sporty>
   no
  </sporty>
 </clothing>
 <clothing>
  <id>
   779254610
  </id>
  <name>
   Adidas Shoes P-5347
  </name>
  <category>
   Shoes
  </category>
  <size>
   L
  </size>
  <color>
   Синий
  </color>
  <material>
   Хлопок
  </material>
  <price>
   505195
  </price>
  <rating>
   2.56
  </rating>
  <reviews>
   787565
  </reviews>
  <new>
   -
  </new>
  <exclusive>
   no
  </exclusive>
  <sporty>
   yes
  </sporty>
 </clothing>
 <clothing>
  <id>
   249360111
  </id>
  <name>
   Converse Socks E-8953
  </name>
  <category>
   Socks
  </category>
  <size>
   XL
  </size>
  <color>
   Фиолетовый
  </color>
  <material>
   Полиэстер
  </material>
  <price>
   731004
  </price>
  <rating>
   2.22
  </rating>
  <reviews>
   368678
  </reviews>
  <new>
   -
  </new>
 </clothing>
 <clothing>
  <id>
   516030029
  </id>
  <name>
   Ellesse Sweater F-8505
  </name>
  <category>
   Sweater
  </category>
  <size>
   S
  </size>
  <color>
   Голубой
  </color>
  <material>
   Шелк
  </material>
  <price>
   959473
  </price>
  <rating>
   1.68
  </rating>
  <reviews>
   763214
  </reviews>
  <new>
   -
  </new>
  <exclusive>
   yes
  </exclusive>
  <sporty>
   yes
  </sporty>
 </clothing>
 <clothing>
  <id>
   215589986
  </id>
  <name>
   Reebok Hat Y-3250
  </name>
  <category>
   Hat
  </category>
  <size>
   M
  </size>
  <color>
   Зеленый
  </color>
  <material>
   Кожа
  </material>
  <price>
   560897
  </price>
  <rating>
   2.61
  </rating>
  <reviews>
   630357
  </reviews>
  <sporty>
   no
  </sporty>
 </clothing>
 <clothing>
  <id>
   304513524
  </id>
  <name>
   Nike Skirt L-7613
  </name>
  <category>
   Skirt
  </category>
  <size>
   XXL
  </size>
  <color>
   Фиолетовый
  </color>
  <material>
   Лен
  </material>
  <price>
   254032
  </price>
  <rating>
   4.92
  </rating>
  <reviews>
   127190
  </reviews>
  <new>
   -
  </new>
  <exclusive>
   no
  </exclusive>
  <sporty>
   yes
  </sporty>
 </clothing>
 <clothing>
  <id>
   319166654
  </id>
  <name>
   Under Armour T-shirt F-3375
  </name>
  <category>
   T-shirt
  </category>
  <size>
   XXL
  </size>
  <color>
   Оранжевый
  </color>
  <material>
   Шерсть
  </material>
  <price>
   214939
  </price>
  <rating>
   2.43
  </rating>
  <reviews>
   97224
  </reviews>
  <new>
   -
  </new>
  <exclusive>
   no
  </exclusive>
  <sporty>
   no
  </sporty>
 </clothing>
 <clothing>
  <id>
   618635120
  </id>
  <name>
   Nike Shirt L-3293
  </name>
  <category>
   Shirt
  </category>
  <size>
   L
  </size>
  <color>
   Фиолетовый
  </color>
  <material>
   Кожа
  </material>
  <price>
   399510
  </price>
  <rating>
   2.43
  </rating>
  <reviews>
   112248
  </reviews>
  <new>
   +
  </new>
  <exclusive>
   yes
  </exclusive>
  <sporty>
   no
  </sporty>
 </clothing>
 <clothing>
  <id>
   310074668
  </id>
  <name>
   PleinSport Dress O-7993
  </name>
  <category>
   Dress
  </category>
  <size>
   XXL
  </size>
  <color>
   Желтый
  </color>
  <material>
   Лен
  </material>
  <price>
   768676
  </price>
  <rating>
   1.2
  </rating>
  <reviews>
   319410
  </reviews>
 </clothing>
 <clothing>
  <id>
   189135405
  </id>
  <name>
   Fila Shirt P-2202
  </name>
  <category>
   Shirt
  </category>
  <size>
   XXL
  </size>
  <color>
   Синий
  </color>
  <material>
   Хлопок
  </material>
  <price>
   554666
  </price>
  <rating>
   1.02
  </rating>
  <reviews>
   32053
  </reviews>
  <exclusive>
   no
  </exclusive>
 </clothing>
 <clothing>
  <id>
   405717850
  </id>
  <name>
   Lacoste Shoes P-4274
  </name>
  <category>
   Shoes
  </category>
  <size>
   M
  </size>
  <color>
   Красный
  </color>
  <material>
   Шерсть
  </material>
  <price>
   143013
  </price>
  <rating>
   3.37
  </rating>
  <reviews>
   391455
  </reviews>
  <exclusive>
   yes
  </exclusive>
 </clothing>
 <clothing>
  <id>
   257946752
  </id>
  <name>
   Under Armour Jacket M-1144
  </name>
  <category>
   Jacket
  </category>
  <size>
   XXL
  </size>
  <color>
   Желтый
  </color>
  <material>
   Лен
  </material>
  <price>
   920250
  </price>
  <rating>
   2.62
  </rating>
  <reviews>
   333136
  </reviews>
  <exclusive>
   no
  </exclusive>
  <sporty>
   yes
  </sporty>
 </clothing>
 <clothing>
  <id>
   224024255
  </id>
  <name>
   Vans Jacket H-3221
  </name>
  <category>
   Jacket
  </category>
  <size>
   S
  </size>
  <color>
   Желтый
  </color>
  <material>
   Кожа
  </material>
  <price>
   645718
  </price>
  <rating>
   4.22
  </rating>
  <reviews>
   485578
  </reviews>
  <new>
   +
  </new>
  <sporty>
   yes
  </sporty>
 </clothing>
 <clothing>
  <id>
   855892836
  </id>
  <name>
   Asics Socks E-9919
  </name>
  <category>
   Socks
  </category>
  <size>
   XXL
  </size>
  <color>
   Оранжевый
  </color>
  <material>
   Полиэстер
  </material>
  <price>
   534083
  </price>
  <rating>
   4.53
  </rating>
  <reviews>
   885465
  </reviews>
  <new>
   +
  </new>
  <exclusive>
   no
  </exclusive>
 </clothing>
 <clothing>
  <id>
   207803541
  </id>
  <name>
   Reebok Belts J-1075
  </name>
  <category>
   Belts
  </category>
  <size>
   XXL
  </size>
  <color>
   Фиолетовый
  </color>
  <material>
   Шерсть
  </material>
  <price>
   713172
  </price>
  <rating>
   4.01
  </rating>
  <reviews>
   650280
  </reviews>
  <new>
   +
  </new>
 </clothing>
 <clothing>
  <id>
   411280266
  </id>
  <name>
   Asics Jeans B-5966
  </name>
  <category>
   Jeans
  </category>
  <size>
   XXL
  </size>
  <color>
   Голубой
  </color>
  <material>
   Полиэстер
  </material>
  <price>
   328060
  </price>
  <rating>
   2.48
  </rating>
  <reviews>
   893703
  </reviews>
  <exclusive>
   yes
  </exclusive>
  <sporty>
   no
  </sporty>
 </clothing>
 <clothing>
  <id>
   840729806
  </id>
  <name>
   Addidas Socks Z-8674
  </name>
  <category>
   Socks
  </category>
  <size>
   M
  </size>
  <color>
   Красный
  </color>
  <material>
   Шерсть
  </material>
  <price>
   622368
  </price>
  <rating>
   3.79
  </rating>
  <reviews>
   558290
  </reviews>
  <new>
   -
  </new>
  <exclusive>
   no
  </exclusive>
  <sporty>
   yes
  </sporty>
 </clothing>
 <clothing>
  <id>
   698477211
  </id>
  <name>
   Vans Pants V-3344
  </name>
  <category>
   Pants
  </category>
  <size>
   XXL
  </size>
  <color>
   Синий
  </color>
  <material>
   Нейлон
  </material>
  <price>
   856535
  </price>
  <rating>
   2.1
  </rating>
  <reviews>
   607778
  </reviews>
  <exclusive>
   no
  </exclusive>
  <sporty>
   no
  </sporty>
 </clothing>
 <clothing>
  <id>
   601298937
  </id>
  <name>
   Ellesse Blouse T-9284
  </name>
  <category>
   Blouse
  </category>
  <size>
   XXL
  </size>
  <color>
   Красный
  </color>
  <material>
   Шерсть
  </material>
  <price>
   107825
  </price>
  <rating>
   2.02
  </rating>
  <reviews>
   827153
  </reviews>
  <new>
   -
  </new>
 </clothing>
 <clothing>
  <id>
   827394921
  </id>
  <name>
   PleinSport Pants Y-6000
  </name>
  <category>
   Pants
  </category>
  <size>
   XXL
  </size>
  <color>
   Оранжевый
  </color>
  <material>
   Лен
  </material>
  <price>
   868226
  </price>
  <rating>
   2.2
  </rating>
  <reviews>
   620356
  </reviews>
  <new>
   -
  </new>
  <sporty>
   no
  </sporty>
 </clothing>
 <clothing>
  <id>
   897413505
  </id>
  <name>
   Puma Shoes B-7284
  </name>
  <category>
   Shoes
  </category>
  <size>
   XXL
  </size>
  <color>
   Желтый
  </color>
  <material>
   Лен
  </material>
  <price>
   196503
  </price>
  <rating>
   2.54
  </rating>
  <reviews>
   894083
  </reviews>
  <exclusive>
   no
  </exclusive>
  <sporty>
   no
  </sporty>
 </clothing>
 <clothing>
  <id>
   321829261
  </id>
  <name>
   Nike T-shirt S-4313
  </name>
  <category>
   T-shirt
  </category>
  <size>
   L
  </size>
  <color>
   Синий
  </color>
  <material>
   Шелк
  </material>
  <price>
   952821
  </price>
  <rating>
   2.02
  </rating>
  <reviews>
   622637
  </reviews>
  <new>
   -
  </new>
  <sporty>
   yes
  </sporty>
 </clothing>
 <clothing>
  <id>
   907385912
  </id>
  <name>
   Converse Blouse J-8618
  </name>
  <category>
   Blouse
  </category>
  <size>
   L
  </size>
  <color>
   Голубой
  </color>
  <material>
   Кожа
  </material>
  <price>
   472175
  </price>
  <rating>
   3.13
  </rating>
  <reviews>
   192597
  </reviews>
  <new>
   -
  </new>
  <exclusive>
   yes
  </exclusive>
  <sporty>
   no
  </sporty>
 </clothing>
 <clothing>
  <id>
   810671632
  </id>
  <name>
   Fila Skirt N-7629
  </name>
  <category>
   Skirt
  </category>
  <size>
   L
  </size>
  <color>
   Желтый
  </color>
  <material>
   Полиэстер
  </material>
  <price>
   233014
  </price>
  <rating>
   2.4
  </rating>
  <reviews>
   697099
  </reviews>
  <new>
   +
  </new>
  <exclusive>
   no
  </exclusive>
  <sporty>
   no
  </sporty>
 </clothing>
 <clothing>
  <id>
   540634516
  </id>
  <name>
   Adidas Gloves L-6333
  </name>
  <category>
   Gloves
  </category>
  <size>
   M
  </size>
  <color>
   Красный
  </color>
  <material>
   Полиэстер
  </material>
  <price>
   505138
  </price>
  <rating>
   4.14
  </rating>
  <reviews>
   161486
  </reviews>
  <new>
   +
  </new>
 </clothing>
 <clothing>
  <id>
   128665232
  </id>
  <name>
   Nike Blouse G-5410
  </name>
  <category>
   Blouse
  </category>
  <size>
   S
  </size>
  <color>
   Зеленый
  </color>
  <material>
   Хлопок
  </material>
  <price>
   815083
  </price>
  <rating>
   4.51
  </rating>
  <reviews>
   58882
  </reviews>
 </clothing>
 <clothing>
  <id>
   328689929
  </id>
  <name>
   PleinSport Handbags L-9347
  </name>
  <category>
   Handbags
  </category>
  <size>
   XXL
  </size>
  <color>
   Фиолетовый
  </color>
  <material>
   Вискоза
  </material>
  <price>
   470212
  </price>
  <rating>
   2.7
  </rating>
  <reviews>
   414158
  </reviews>
  <new>
   +
  </new>
  <exclusive>
   no
  </exclusive>
 </clothing>
 <clothing>
  <id>
   685494720
  </id>
  <name>
   Nike Handbags F-6962
  </name>
  <category>
   Handbags
  </category>
  <size>
   XXL
  </size>
  <color>
   Красный
  </color>
  <material>
   Хлопок
  </material>
  <price>
   270917
  </price>
  <rating>
   1.76
  </rating>
  <reviews>
   647629
  </reviews>
  <sporty>
   no
  </sporty>
 </clothing>
 <clothing>
  <id>
   231591124
  </id>
  <name>
   New Balance Shirt X-1769
  </name>
  <category>
   Shirt
  </category>
  <size>
   M
  </size>
  <color>
   Красный
  </color>
  <material>
   Полиэстер
  </material>
  <price>
   940909
  </price>
  <rating>
   2.64
  </rating>
  <reviews>
   449335
  </reviews>
  <exclusive>
   no
  </exclusive>
 </clothing>
 <clothing>
  <id>
   855404374
  </id>
  <name>
   Puma Socks T-4051
  </name>
  <category>
   Socks
  </category>
  <size>
   L
  </size>
  <color>
   Синий
  </color>
  <material>
   Кожа
  </material>
  <price>
   710055
  </price>
  <rating>
   1.34
  </rating>
  <reviews>
   446291
  </reviews>
  <exclusive>
   no
  </exclusive>
 </clothing>
 <clothing>
  <id>
   787973913
  </id>
  <name>
   Reebok Pants L-8818
  </name>
  <category>
   Pants
  </category>
  <size>
   S
  </size>
  <color>
   Голубой
  </color>
  <material>
   Вискоза
  </material>
  <price>
   984623
  </price>
  <rating>
   4.53
  </rating>
  <reviews>
   415060
  </reviews>
  <new>
   -
  </new>
  <sporty>
   no
  </sporty>
 </clothing>
 <clothing>
  <id>
   735539199
  </id>
  <name>
   Adidas Blouse J-5243
  </name>
  <category>
   Blouse
  </category>
  <size>
   XXL
  </size>
  <color>
   Красный
  </color>
  <material>
   Полиэстер
  </material>
  <price>
   761935
  </price>
  <rating>
   2.42
  </rating>
  <reviews>
   192899
  </reviews>
  <new>
   -
  </new>
  <exclusive>
   no
  </exclusive>
 </clothing>
 <clothing>
  <id>
   716868521
  </id>
  <name>
   Fila Shoes T-5591
  </name>
  <category>
   Shoes
  </category>
  <size>
   M
  </size>
  <color>
   Зеленый
  </color>
  <material>
   Кожа
  </material>
  <price>
   495604
  </price>
  <rating>
   4.5
  </rating>
  <reviews>
   289790
  </reviews>
  <sporty>
   no
  </sporty>
 </clothing>
 <clothing>
  <id>
   511637468
  </id>
  <name>
   New Balance Sweater G-1387
  </name>
  <category>
   Sweater
  </category>
  <size>
   S
  </size>
  <color>
   Желтый
  </color>
  <material>
   Хлопок
  </material>
  <price>
   561790
  </price>
  <rating>
   2.23
  </rating>
  <reviews>
   319928
  </reviews>
  <exclusive>
   yes
  </exclusive>
  <sporty>
   yes
  </sporty>
 </clothing>
 <clothing>
  <id>
   178796077
  </id>
  <name>
   Lacoste T-shirt D-6510
  </name>
  <category>
   T-shirt
  </category>
  <size>
   XXL
  </size>
  <color>
   Фиолетовый
  </color>
  <material>
   Полиэстер
  </material>
  <price>
   403072
  </price>
  <rating>
   4.55
  </rating>
  <reviews>
   930524
  </reviews>
  <new>
   -
  </new>
  <exclusive>
   no
  </exclusive>
  <sporty>
   no
  </sporty>
 </clothing>
 <clothing>
  <id>
   370090851
  </id>
  <name>
   Ellesse Hat M-6903
  </name>
  <category>
   Hat
  </category>
  <size>
   L
  </size>
  <color>
   Оранжевый
  </color>
  <material>
   Шерсть
  </material>
  <price>
   690208
  </price>
  <rating>
   3.6
  </rating>
  <reviews>
   511714
  </reviews>
  <new>
   -
  </new>
  <exclusive>
   no
  </exclusive>
  <sporty>
   no
  </sporty>
 </clothing>
 <clothing>
  <id>
   747197341
  </id>
  <name>
   PleinSport Sweater U-3691
  </name>
  <category>
   Sweater
  </category>
  <size>
   XXL
  </size>
  <color>
   Фиолетовый
  </color>
  <material>
   Полиэстер
  </material>
  <price>
   302693
  </price>
  <rating>
   4.44
  </rating>
  <reviews>
   452245
  </reviews>
  <exclusive>
   yes
  </exclusive>
  <sporty>
   yes
  </sporty>
 </clothing>
 <clothing>
  <id>
   149812076
  </id>
  <name>
   Fila Shoes Q-1746
  </name>
  <category>
   Shoes
  </category>
  <size>
   S
  </size>
  <color>
   Фиолетовый
  </color>
  <material>
   Шелк
  </material>
  <price>
   637201
  </price>
  <rating>
   3.09
  </rating>
  <reviews>
   667398
  </reviews>
  <new>
   -
  </new>
  <sporty>
   no
  </sporty>
 </clothing>
</clothing-items>
